{ "compressionlevel":-1,
 "editorsettings":
    {
     "export":
        {
         "target":"."
        }
    },
 "height":34,
 "infinite":false,
 "layers":[
        {
         "draworder":"topdown",
         "id":3,
         "name":"Level",
         "objects":[
                {
                 "height":0,
                 "id":3,
                 "name":"Player",
                 "point":true,
                 "rotation":0,
                 "type":"Player",
                 "visible":true,
                 "width":0,
                 "x":248,
                 "y":128
                }, 
                {
                 "height":256,
                 "id":4,
                 "name":"Bounds",
                 "rotation":0,
                 "type":"Bounds",
                 "visible":true,
                 "width":464,
                 "x":8,
                 "y":8
                }, 
                {
                 "height":48,
                 "id":9,
                 "name":"Box",
                 "rotation":0,
                 "type":"Box",
                 "visible":true,
                 "width":48,
                 "x":32,
                 "y":104
                }, 
                {
                 "height":48,
                 "id":10,
                 "name":"Box",
                 "rotation":0,
                 "type":"Box",
                 "visible":true,
                 "width":48,
                 "x":400,
                 "y":104
                }],
         "opacity":1,
         "type":"objectgroup",
         "visible":false,
         "x":0,
         "y":0
        }, 
        {
         "draworder":"topdown",
         "id":5,
         "name":"Objects",
         "objects":[
                {
                 "height":248,
                 "id":11,
                 "name":"Objects",
                 "properties":[
                        {
                         "name":"Bonus.Woman",
                         "type":"int",
                         "value":2
                        }, 
                        {
                         "name":"Electrode",
                         "type":"int",
                         "value":5
                        }, 
                        {
                         "name":"Grunt",
                         "type":"int",
                         "value":10
                        }],
                 "rotation":0,
                 "type":"Objects",
                 "visible":true,
                 "width":456,
                 "x":12,
                 "y":12
                }],
         "opacity":1,
         "type":"objectgroup",
         "visible":true,
         "x":0,
         "y":0
        }],
 "nextlayerid":6,
 "nextobjectid":14,
 "orientation":"orthogonal",
 "renderorder":"right-down",
 "tiledversion":"1.4.2",
 "tileheight":8,
 "tilesets":[],
 "tilewidth":8,
 "type":"map",
 "version":1.4,
 "width":60
}